README.md
setup.py
memlib/__init__.py
memlib.egg-info/PKG-INFO
memlib.egg-info/SOURCES.txt
memlib.egg-info/dependency_links.txt
memlib.egg-info/top_level.txt